BasicCalculator/__init__.py
BasicCalculator/calculator/__init__.py
BasicCalculator/calculator/calc.py
BasicCalculator/ui/__init__.py
BasicCalculator/ui/gui.py
pyBasicCalculator-0.0.1.dist-info/METADATA
pyBasicCalculator-0.0.1.dist-info/WHEEL
pyBasicCalculator-0.0.1.dist-info/entry_points.txt
pyBasicCalculator-0.0.1.dist-info/top_level.txt
pyBasicCalculator-0.0.1.dist-info/RECORD
