Metadata-Version: 2.1
Name: pyBasicCalculator
Version: 0.0.1
Summary: A very basic calculator with both CLI and GUI using Qt
Author-email: Meer Suri <meersuri@gmail.com>
Project-URL: Homepage, https://github.com/meersuri/basic-calculator
Project-URL: Bug Tracker, https://github.com/meersuri/basic-calculator/issues
Classifier: Programming Language :: Python :: 3
Classifier: License :: OSI Approved :: MIT License
Classifier: Operating System :: OS Independent
Requires-Python: >=3.7
Requires-Dist: PySide2
